petpet/__init__.py
petpet/petpet.py
petpet/saveGif.py
petpet/setup.py
petpet-2.0.1.dist-info/METADATA
petpet-2.0.1.dist-info/WHEEL
petpet-2.0.1.dist-info/top_level.txt
petpet-2.0.1.dist-info/RECORD
